cedarpy-4.8.0.dist-info/METADATA
cedarpy-4.8.0.dist-info/WHEEL
cedarpy-4.8.0.dist-info/licenses/LICENSE
cedarpy/__init__.py
cedarpy/_internal.cpython-39-aarch64-linux-gnu.so
cedarpy/cedarpy.pyi
cedarpy/py.typed
cedarpy-4.8.0.dist-info/RECORD
