Metadata-Version: 2.4
Name: cedarpy
Version: 4.8.0
Classifier: Programming Language :: Rust
Classifier: Programming Language :: Python :: Implementation :: CPython
Classifier: Programming Language :: Python :: Implementation :: PyPy
Requires-Dist: maturin>=1.8,<2 ; extra == 'dev'
Requires-Dist: parameterized==0.9.0 ; extra == 'dev'
Requires-Dist: pip-tools>=7.4.1 ; extra == 'dev'
Requires-Dist: pytest==7.4.0 ; extra == 'dev'
Requires-Dist: pytest-benchmark>=4.0.0 ; extra == 'dev'
Provides-Extra: dev
License-File: LICENSE
Requires-Python: >=3.9
